odoo/addons/ssi_hr_employee_project_experience/README.rst
odoo/addons/ssi_hr_employee_project_experience/__init__.py
odoo/addons/ssi_hr_employee_project_experience/__manifest__.py
odoo/addons/ssi_hr_employee_project_experience/models/__init__.py
odoo/addons/ssi_hr_employee_project_experience/models/hr_employee.py
odoo/addons/ssi_hr_employee_project_experience/models/hr_employee_project_experience.py
odoo/addons/ssi_hr_employee_project_experience/security/ir.model.access.csv
odoo/addons/ssi_hr_employee_project_experience/static/description/icon.png
odoo/addons/ssi_hr_employee_project_experience/views/hr_employee_views.xml
odoo14_addon_ssi_hr_employee_project_experience-14.0.1.2.0.dist-info/METADATA
odoo14_addon_ssi_hr_employee_project_experience-14.0.1.2.0.dist-info/WHEEL
odoo14_addon_ssi_hr_employee_project_experience-14.0.1.2.0.dist-info/top_level.txt
odoo14_addon_ssi_hr_employee_project_experience-14.0.1.2.0.dist-info/RECORD
